adminui/__init__.py
adminui/actions.py
adminui/app.py
adminui/chart.py
adminui/element.py
adminui/feedback.py
adminui/form.py
adminui/layout.py
adminui/page.py
adminui/table.py
adminui/static/asset-manifest.json
adminui/static/favicon.png
adminui/static/index.html
adminui/static/layouts__BasicLayout.826d66d2.async.js
adminui/static/layouts__BasicLayout.eed97ba8.chunk.css
adminui/static/layouts__UserLayout.b2af8755.chunk.css
adminui/static/layouts__UserLayout.cb503ac1.async.js
adminui/static/menu.json
adminui/static/p__404.f9cc51ff.async.js
adminui/static/p__index.8537a62a.async.js
adminui/static/p__index.8c6fddb2.chunk.css
adminui/static/p__user__login.15d548f3.async.js
adminui/static/p__user__login.b40f234b.chunk.css
adminui/static/umi.136a0fd4.js
adminui/static/umi.939a4b96.css
adminui/static/vendors.5c22fc9a.chunk.css
adminui/static/vendors.9598e126.async.js
adminui/static/icons/icon-128x128.png
adminui/static/icons/icon-192x192.png
adminui/static/icons/icon-512x512.png
example_shared_app/__init__.py
example_shared_app/detail.py
example_shared_app/main.py
tests/__init__.py
tests/test_app.py
tests/test_form.py
adminui-1.5.2.dist-info/LICENSE
adminui-1.5.2.dist-info/METADATA
adminui-1.5.2.dist-info/WHEEL
adminui-1.5.2.dist-info/top_level.txt
adminui-1.5.2.dist-info/RECORD
